{"id":"12-medium-1178","theme":"quartet","grid":"AIXHPUXBNPUCRMTQESNAEEOOHWATRIORODYNOQJDLVCBRHNCVIZOEUOEOXHEAUIVSUMRLFERNVNSCTSSGLTTTEIUEVIHGROOOOTTXPTOZVOENNXCVQAPESLGREPERTOIREXPSAORCHESTRAL","solution":"108;3;10;PERCUSSION,73;3;6;VIOLIN,27;0;4;TRIO,7;1;10;BARBERSHOP,60;1;5;ANTON,54;3;4;OBOE,120;0;10;REPERTOIRE,42;2;5;CELLO,132;3;6;SEXTET,134;0;10;ORCHESTRAL,0;2;7;AMADEUS,11;1;8;CONCERTO","gridSize":12,"difficulty":"medium","wordCount":12,"wordlist":["OBOE","TRIO","ANTON","CELLO","SEXTET","VIOLIN","AMADEUS","CONCERTO","BARBERSHOP","ORCHESTRAL","PERCUSSION","REPERTOIRE"]}