{"id":"12-medium-1185","theme":"beach","grid":"JIFRFPUZZLEXUUELKFGKGRAMUBRFNEWPORTOZOOGSUCINCIPDUSTNGJWSEVHRLIGHTHOUSEAMEOTIDELCLPRIVNLBPOZQLCBAALGSOAGEYTOMRZRSNYLFLYUIDGBSRTSMEMRFLORIDAUMZBP","solution":"132;0;7;FLORIDA,42;0;6;PICNIC,61;0;10;LIGHTHOUSE,88;2;4;BOYS,14;1;7;EROSION,28;0;7;NEWPORT,72;1;5;MIAMI,89;2;4;PALM,5;0;6;PUZZLE,59;1;7;HARBOUR,25;1;9;BOULEVARD,75;0;4;TIDE","gridSize":12,"difficulty":"medium","wordCount":12,"wordlist":["BOYS","PALM","TIDE","MIAMI","PICNIC","PUZZLE","EROSION","FLORIDA","HARBOUR","NEWPORT","BOULEVARD","LIGHTHOUSE"]}