{"id":"12-medium-1201","theme":"beach","grid":"CALIFORNIADRWWSQDBWOCEANAAMWCCYEVUWHCBVMIBJSQMCAYOXERMSOCCERYUSVSLMCBTEBFLVXYDFIWGSOSECLIFFSNNHUVVQZWEVOCGORFAXHLSMZHKRFEROSIONDZMERRDLIGHTHOUSE","solution":"19;0;5;OCEAN,101;0;4;COVE,14;2;8;SWIMMING,54;0;6;SOCCER,35;1;7;HARBOUR,134;0;10;LIGHTHOUSE,37;1;9;BOULEVARD,0;0;10;CALIFORNIA,120;0;7;EROSION,82;1;5;SHORE,86;0;6;CLIFFS,12;2;5;WAVES","gridSize":12,"difficulty":"medium","wordCount":12,"wordlist":["COVE","OCEAN","SHORE","WAVES","CLIFFS","SOCCER","EROSION","HARBOUR","SWIMMING","BOULEVARD","CALIFORNIA","LIGHTHOUSE"]}