{"id":"12-medium-1553","theme":"beach","grid":"CBEMDNGDSAFJMRYLFNNNILRUHEJJIARNOORWOCCDLERRBEZETONNIOIRCFTWEAIPFDACAHIZLSIIAHOXTRKFSTLBMSNWLGHJTALIGHTHOUSECLFISHINGLWRVYYKAXWPWSTWXTOURISTVPCI","solution":"98;0;10;LIGHTHOUSE,72;3;7;LANDING,89;3;6;SOCCER,62;3;6;INLAND,76;3;7;FLORIDA,133;0;7;TOURIST,37;1;7;COASTAL,63;3;4;PIER,110;0;7;FISHING,108;3;10;CALIFORNIA,24;1;6;HOTELS,77;3;6;HARBOR","gridSize":12,"difficulty":"medium","wordCount":12,"wordlist":["PIER","HARBOR","HOTELS","INLAND","SOCCER","COASTAL","FISHING","FLORIDA","LANDING","TOURIST","CALIFORNIA","LIGHTHOUSE"]}