{"id":"12-medium-1562","theme":"prophecy","grid":"DBHPROPHETSHJISAIAHSJIEOFBVBIBLICALUULPIRSGCDESBDEZUNNSASQTGJJZLIEMEGOXAVOHLAMSAMEURGRAZAOHSKFKXGERHMHBWRLKRHIUFORETELLSMMGPREDICTSAZFHJQBVFXWOY","solution":"100;3;5;MOSES,121;3;8;MUHAMMAD,2;2;7;MESSIAH,27;0;8;BIBLICAL,120;3;5;MIRZA,13;0;6;ISAIAH,3;0;8;PROPHETS,108;3;7;HEALING,0;2;6;DIVINE,111;0;9;FORETELLS,1;1;5;BIBLE,123;0;8;PREDICTS","gridSize":12,"difficulty":"medium","wordCount":12,"wordlist":["BIBLE","MIRZA","MOSES","DIVINE","ISAIAH","HEALING","MESSIAH","BIBLICAL","MUHAMMAD","PREDICTS","PROPHETS","FORETELLS"]}