{"id":"12-medium-1572","theme":"wind","grid":"NTHFNSFOLOSMAGTECTHWZZCURGEOTHERMALGHEQNXRMKSIUZBENSEROAGSUURLAEORIPMENVALOTWLARIKXMHSSWSAATNCFNMATPSFBRIPACYXXCEZWLCNCLZKKGEEENERGYCEYNOZDFYTZU","solution":"36;2;4;HEAT,48;2;5;BLOWS,86;3;5;STORM,51;2;5;SOLAR,13;2;10;GENERATING,86;2;5;SPEED,24;2;9;RENEWABLE,88;3;5;SAILS,126;0;6;ENERGY,25;0;10;GEOTHERMAL,101;3;5;FARMS,28;2;8;TROPICAL","gridSize":12,"difficulty":"medium","wordCount":12,"wordlist":["HEAT","BLOWS","FARMS","SAILS","SOLAR","SPEED","STORM","ENERGY","TROPICAL","RENEWABLE","GENERATING","GEOTHERMAL"]}