{"id":"12-medium-1694","theme":"beach","grid":"NMVGFAFACGPQEMPNSHOREXFJWCIISNXWKJMDPDCDRONENPMZODNNRHARBOURRAIAHWMHUCQATYCLBCHWMOETOTOCEANDZVDCIOMSKMDUNESXHNUWWHARBORDUAHSPZINLANDUUAIEROSIONR","solution":"3;1;7;LANDING,16;0;5;SHORE,113;0;6;HARBOR,126;0;6;INLAND,86;0;5;OCEAN,69;1;4;COVE,49;1;7;DAYTONA,53;0;7;HARBOUR,14;1;6;PICNIC,102;0;5;DUNES,136;0;7;EROSION,0;1;7;NEWPORT","gridSize":12,"difficulty":"medium","wordCount":12,"wordlist":["COVE","DUNES","OCEAN","SHORE","HARBOR","INLAND","PICNIC","DAYTONA","EROSION","HARBOUR","LANDING","NEWPORT"]}