{"id":"12-medium-1796","theme":"myth","grid":"GMYTHOLOGYSGCREATIONTSVMEOREAVTLEKTYOYQPLJUDZWEYXSLMACDNEYWUBIIVCOINRIFIJUGRGGTOXETJFTNRIITRIJLYYLSRESQLMMMSSGOTNEEJBCKSPSHORBKUHWSNAHBLDHITGKGM","solution":"101;3;5;STORY,122;3;9;TWENTIETH,43;2;5;DEITY,74;2;5;GREEK,76;3;7;GODDESS,110;3;6;ORIGIN,36;2;6;OSIRIS,84;2;5;FLOOD,1;0;9;MYTHOLOGY,125;3;6;BELIEF,53;3;4;CULT,12;0;8;CREATION","gridSize":12,"difficulty":"medium","wordCount":12,"wordlist":["CULT","DEITY","FLOOD","GREEK","STORY","BELIEF","ORIGIN","OSIRIS","GODDESS","CREATION","MYTHOLOGY","TWENTIETH"]}