{"id":"12-medium-1844","theme":"courage","grid":"TFULDKGHSJZCETZTIXJJRNPOSLBMDDOTKCQNHAEJLAMVDABSKOCAPONOEVLCTOPRDOSGTFBISGUEIESPEAUEZOELYFRKIRNNHRDKJUISIRLCFYHZGCKCHLIENROPFZKIEILTQTMBHWYTUDPN","solution":"78;2;5;SKILL,66;2;6;SPIRIT,25;2;10;LEADERSHIP,24;2;9;SACRIFICE,87;3;4;LION,139;3;4;TELL,11;1;10;CONSCIENCE,36;2;4;HOPE,28;2;6;DANGER,108;3;7;FREEDOM,138;0;4;DUTY","gridSize":12,"difficulty":"medium","wordCount":11,"wordlist":["DUTY","HOPE","LION","TELL","SKILL","DANGER","SPIRIT","FREEDOM","SACRIFICE","CONSCIENCE","LEADERSHIP"]}