{"id":"12-medium-1980","theme":"beach","grid":"BLIUXWCWSENFCLEMBEACHESISOARAVUVVTBQHIANOIXMEAOXOFGSDSMPJSURRIWOTIIGHSLJESDDJANOCDEJVHXJZPLGNNVVPIFCTALKINAIINHGWLXEZFRXEGKGTMUBTODLRFUJVKINLAND","solution":"2;2;5;MIAMI,12;2;7;COASTAL,16;0;7;BEACHES,13;2;7;LANDING,89;1;4;PALM,138;0;6;INLAND,96;1;4;PIER,5;2;5;WAVES,14;2;7;EROSION,34;1;9;BOULEVARD,49;1;7;FISHING,24;1;5;SHORE","gridSize":12,"difficulty":"medium","wordCount":12,"wordlist":["PALM","PIER","MIAMI","SHORE","WAVES","INLAND","BEACHES","COASTAL","EROSION","FISHING","LANDING","BOULEVARD"]}