{"id":"12-medium-2341","theme":"beach","grid":"UZOSEVAWEFSFTHYCSNJCMGYLEOJNOOGOWCAOBTUJKARVTIGREEERNESEPKUIALIRISCTZAYDCSVPUSCAAPUAHTIDECTZILWHEOYRDAYTONAMSQWEKVROCXFTRMNFISHINGUUTLVUPQVDNLAD","solution":"100;0;7;DAYTONA,85;0;4;TIDE,11;1;7;FLORIDA,36;1;7;BEACHES,75;3;4;PIER,19;1;4;COVE,15;2;7;COASTAL,36;3;4;BOYS,3;0;5;WAVES,13;1;6;HOTELS,12;2;7;TOURIST,123;0;7;FISHING","gridSize":12,"difficulty":"medium","wordCount":12,"wordlist":["BOYS","COVE","PIER","TIDE","WAVES","HOTELS","BEACHES","COASTAL","DAYTONA","FISHING","FLORIDA","TOURIST"]}