{"id":"12-medium-2437","theme":"poltergeist","grid":"FPAHHEUUKMZHMASCTANJTOTXERNOTRUTGUSDXAAEUIINIVWBPNPFMNVCTTWMLOASAODIKIYAARRTTHNTTENZIMTRWWSERYRGNAMASOSBHARYELENHAAPEPCKDKNGCHLBCJQKBLTEWYIMPTQP","solution":"2;2;8;ACTIVITY,13;2;9;PHENOMENA,124;3;4;CASE,123;3;5;GHOST,1;1;10;PARANORMAL,16;2;8;TRICKERY,14;2;10;SOUNDTRACK,4;2;8;HAUNTING,63;1;7;STRANGE,5;2;6;ENTITY,24;1;9;EXPLAINED,38;1;9;APARTMENT","gridSize":12,"difficulty":"medium","wordCount":12,"wordlist":["CASE","GHOST","ENTITY","STRANGE","ACTIVITY","HAUNTING","TRICKERY","APARTMENT","EXPLAINED","PHENOMENA","PARANORMAL","SOUNDTRACK"]}