{"id":"12-medium-2445","theme":"blog","grid":"COMMENTARYEDDUSETADPUTENNYPGSVSFNTOZJGOTQYYEAIVGKBSULRMDSRKYVOIITMPSQOBOPGANOUUWOFNVVDECMCBBJTFLAFOHSEEEHMZOJGXITCDINNSJBPDLAMCIRMHZQCZFANLPABPV","solution":"85;3;5;DAILY,72;3;5;POSTS,25;2;7;YOUTUBE,122;3;10;DISCUSSION,86;3;5;ENTRY,87;3;7;COMMENT,135;3;8;FACEBOOK,14;0;7;UPDATES,77;3;7;UPDATED,0;0;10;COMMENTARY,88;2;5;MEDIA,99;2;4;HTML","gridSize":12,"difficulty":"medium","wordCount":12,"wordlist":["HTML","DAILY","ENTRY","MEDIA","POSTS","COMMENT","UPDATED","UPDATES","YOUTUBE","FACEBOOK","COMMENTARY","DISCUSSION"]}