{"id":"12-medium-246","theme":"cruise","grid":"DDGKSSMSSMZJEEEHPNAAOPHLSPEXERCISESITLINERHLNVQZROCJDSMIGUGSOYJDEORBSHLNYMYATAOAAZWREESAMNMFNITRRNNBCAFHZOUFQTUQHHHKYLYDPSVALBTGFSRPNSBBAXBIZQOX","solution":"98;3;4;NATO,86;3;4;SEAS,1;1;10;DEPLOYMENT,0;1;9;DESTROYER,121;3;9;SUBMARINE,26;0;9;EXERCISES,7;1;4;SAIL,4;1;5;SPEED,6;1;4;MACH,37;0;5;LINER,74;2;5;YACHT,134;3;7;BAHAMAS","gridSize":12,"difficulty":"medium","wordCount":12,"wordlist":["MACH","NATO","SAIL","SEAS","LINER","SPEED","YACHT","BAHAMAS","DESTROYER","EXERCISES","SUBMARINE","DEPLOYMENT"]}