{"id":"12-medium-2640","theme":"beach","grid":"VDXCFSEHCAEBBOULEVARDTZLFISHINGKTIUARCUPSCMEIPTNAKHJUWOYDTTDDSATKZIAENSICHNOPSZMSVBNUODUROVLMTYGQRBRKCUMEIABUEAIMCABBXNLPBLSJEPCWDEGDHLTTRZICXGF","solution":"77;1;6;SOCCER,41;2;7;COASTAL,24;0;7;FISHING,63;1;7;TOURIST,61;1;5;SHORE,5;0;7;BEACHES,40;2;8;SWIMMING,32;1;4;TIDE,50;1;8;HANDBALL,39;2;6;PUZZLE,23;1;7;LANDING,12;0;9;BOULEVARD","gridSize":12,"difficulty":"medium","wordCount":12,"wordlist":["TIDE","SHORE","PUZZLE","SOCCER","BEACHES","COASTAL","FISHING","LANDING","TOURIST","HANDBALL","SWIMMING","BOULEVARD"]}