{"id":"12-medium-2769","theme":"floral","grid":"MLAHOPYRZNCIVLZPKVEJOMKWSGTCPDRIGXZYEEOCNETVIXGRCLYEIANMSOOFCEVURMSDLHQSBAIOENUOAUYFLDCLGBHCIGLXUEBIIPGOXLERDMSFRNHEDTSSEEUOSJGXXNNHDQMFLOWERING","solution":"132;3;7;DESIGNS,108;3;10;DECORATION,120;3;6;EMBLEM,84;3;8;LAVENDER,2;2;10;APPENDAGES,89;3;4;BUDS,134;3;10;MORPHOLOGY,48;2;7;CEILING,135;0;9;FLOWERING,60;3;5;CLOCK,79;2;4;OILS","gridSize":12,"difficulty":"medium","wordCount":11,"wordlist":["BUDS","OILS","CLOCK","EMBLEM","CEILING","DESIGNS","LAVENDER","FLOWERING","APPENDAGES","DECORATION","MORPHOLOGY"]}