{"id":"12-medium-2895","theme":"vampire","grid":"UKVSDZUSBDNJMSILPHRINWGVYWBLAIEESKZNSFULLDKLJTNOTKXSAEAEHJGMEQDLETRGAOUGRKBWRIIRWQCNISKOJLROOGQSEFMBNOBAMSDFSMEUIASVIGTJISSHMTISJDKOFMASQUERADEO","solution":"75;3;7;WEEKEND,74;3;5;BLADE,120;3;8;IMMORTAL,1;2;6;KILLER,51;2;7;DIARIES,122;3;8;SUNLIGHT,88;2;4;JOSS,133;0;10;MASQUERADE,99;2;4;BITE,3;2;5;SPIKE,2;2;4;VLAD,12;1;9;MYSTERIES","gridSize":12,"difficulty":"medium","wordCount":12,"wordlist":["BITE","JOSS","VLAD","BLADE","SPIKE","KILLER","DIARIES","WEEKEND","IMMORTAL","SUNLIGHT","MYSTERIES","MASQUERADE"]}