{"id":"12-medium-3073","theme":"beach","grid":"WWGJYDCWHCVVXXQOBLAVALPTDYWCOILMRIQLANXEUGIUBFCLYRHALHFFOFOATZANETOQRSABOFRFVHRUVCSDNTBSAONZHOTNAIOYRUIZNVAAQDUFDSASCELHSERLBEVNBUNONFKIOPXNPVHE","solution":"8;1;6;HARBOR,6;1;10;CALIFORNIA,24;1;7;DAYTONA,81;1;4;COVE,85;1;4;TIDE,16;1;9;BOULEVARD,15;1;5;OCEAN,46;1;7;COASTAL,17;1;10;LIGHTHOUSE,35;1;8;HANDBALL,50;1;7;HARBOUR,9;1;6;CLIFFS","gridSize":12,"difficulty":"medium","wordCount":12,"wordlist":["COVE","TIDE","OCEAN","CLIFFS","HARBOR","COASTAL","DAYTONA","HARBOUR","HANDBALL","BOULEVARD","CALIFORNIA","LIGHTHOUSE"]}