{"id":"12-medium-3152","theme":"meadow","grid":"BIPTHISTLEUVYDROPKEVAUWORKAQEOIEECXRAGIEJRNLHKSJTSRMWILDLIFEUCIAPTHAMESZBUELSWVCQJRDIRAFESOUGOVVRDTYJYLRNVFKTEUKQPKATBYSWZROQWMZNHMONOTIFIEDZDKH","solution":"16;2;4;POND,86;3;6;ALPINE,52;0;8;WILDLIFE,61;3;5;CREEK,65;0;6;THAMES,37;2;9;GRASSLAND,12;1;9;TRIBUTARY,2;1;7;PRAIRIE,77;2;5;WORTH,126;3;5;MANOR,3;0;7;THISTLE,132;0;8;NOTIFIED","gridSize":12,"difficulty":"medium","wordCount":12,"wordlist":["POND","CREEK","MANOR","WORTH","ALPINE","THAMES","PRAIRIE","THISTLE","NOTIFIED","WILDLIFE","GRASSLAND","TRIBUTARY"]}