{"id":"12-medium-3295","theme":"beach","grid":"MVPTNDAYTONAKDUKRTSOOAYEVHCEBEACHESNBCLIFFSEDJBEHEAZHARBOREWIARPALMFLFYPUYNOTIDEZIXOGRRDSAELZSJRWGDPBIUTCHNTBBNQTAOUOIMHIRXQDSLNVNHVRXMIAMILEGUP","solution":"104;1;4;COVE,48;2;8;HANDBALL,28;0;7;BEACHES,49;2;7;EROSION,5;0;7;DAYTONA,63;0;4;PALM,35;1;7;NEWPORT,134;0;5;MIAMI,76;0;4;TIDE,69;1;7;FISHING,52;0;6;HARBOR,37;0;6;CLIFFS","gridSize":12,"difficulty":"medium","wordCount":12,"wordlist":["COVE","PALM","TIDE","MIAMI","CLIFFS","HARBOR","BEACHES","DAYTONA","EROSION","FISHING","NEWPORT","HANDBALL"]}