{"id":"12-medium-3339","theme":"summer","grid":"VAYHOLIDAYSIJQOCSSIWTSGUJWXRJSZGCWLCRZVACATIONEVSELYLBTRLLKMWQHWZEHLYPXQICKALTATMVDPMDPHNFSUPVMNMETTNEJXIAHUIATIESDWCLVNNBARCELONAYVGRFKEAMFLFRB","solution":"134;3;9;FREESTYLE,133;3;8;RAINFALL,44;1;7;OLYMPIC,109;3;9;ATHLETICS,77;3;5;THROW,38;0;8;VACATION,84;2;5;METRE,121;0;9;BARCELONA,48;1;8;SWIMMING,3;0;8;HOLIDAYS,102;3;4;JUMP,116;3;4;CAMP","gridSize":12,"difficulty":"medium","wordCount":12,"wordlist":["CAMP","JUMP","METRE","THROW","OLYMPIC","HOLIDAYS","RAINFALL","SWIMMING","VACATION","ATHLETICS","BARCELONA","FREESTYLE"]}