{"id":"12-medium-335","theme":"vault","grid":"ICHJAVELINTREWRTHFPOOPHFBLBIAMOREVMRYHSSUEOSMDOEXXMJGRNIXOASDECORATEDMYCFLOORIDNBDVOCFHTIIIIXKLEDCMAUSOLEUMSRFARCHESKSKTHCENVAULTINGHRBFDNABDVAW","solution":"87;3;8;TRANSEPT,2;2;7;BENEATH,60;0;9;DECORATED,86;3;6;HORROR,98;0;9;MAUSOLEUM,90;3;6;INDOOR,110;0;6;ARCHES,23;1;8;FRESCOES,72;0;5;FLOOR,51;3;4;JUMP,3;0;7;JAVELIN,124;0;8;VAULTING","gridSize":12,"difficulty":"medium","wordCount":12,"wordlist":["JUMP","FLOOR","ARCHES","HORROR","INDOOR","BENEATH","JAVELIN","FRESCOES","TRANSEPT","VAULTING","DECORATED","MAUSOLEUM"]}