{"id":"12-medium-3428","theme":"surrealism","grid":"GFIGURATIVEAETGCIWVCLQNMODOGIVIPGTSFMAGRITTESIGNEDAKEGSILNTRTASOJSLAIAUYRHPPVAMTTOUJIFYWEINKMNECCGRRNIAUADADFLRIARHEYQAFJUMPLTMWDXYMSALVADORVGOZ","solution":"74;3;6;POETIC,36;0;8;MAGRITTE,15;2;9;FANTASTIC,122;3;10;MINIMALISM,0;1;9;GEOMETRIC,132;3;10;SURREALIST,123;3;8;PAINTING,114;3;6;HUMOUR,25;1;4;DADA,1;0;10;FIGURATIVE,132;0;8;SALVADOR","gridSize":12,"difficulty":"medium","wordCount":11,"wordlist":["DADA","HUMOUR","POETIC","MAGRITTE","PAINTING","SALVADOR","FANTASTIC","GEOMETRIC","FIGURATIVE","MINIMALISM","SURREALIST"]}