{"id":"12-medium-3472","theme":"stripes","grid":"BXUNDERSIDETLLFITZZPJWFTHSOONNYHWPTROYNTRSZEWDSEREDOCEIIXHMCILWGUHVGRRAIZLUNCTEENMLPOOGNRCMSRIZINWIIFKZFAOAETIHIGQETZWFNASBZMYDOHGDTLHWGFYSEGXCS","solution":"14;2;7;FOREVER,62;3;4;WORN,0;2;8;BLOTCHES,25;2;5;SNOUT,98;3;4;INCH,37;1;9;YELLOWISH,24;1;10;HORIZONTAL,15;2;8;INSIGNIA,121;3;5;SHIRT,2;0;9;UNDERSIDE,115;3;4;TAIL,35;1;10;RECIPIENTS","gridSize":12,"difficulty":"medium","wordCount":12,"wordlist":["INCH","TAIL","WORN","SHIRT","SNOUT","FOREVER","BLOTCHES","INSIGNIA","UNDERSIDE","YELLOWISH","HORIZONTAL","RECIPIENTS"]}