{"id":"12-medium-3482","theme":"hibernation","grid":"VNDDEDSTIIJCGEEIRYOVYXLXESTSAVCLGYCFSTXKTPZATDHMTIBWQZAIVVHXAVGVIAVUREWVTARRIIEOSNSEITGJTCPTSEOOOIKCIRSJYXMVNOAMOEYKLXTEVNQTNNURQJWLIDBAWAKENEDW","solution":"124;3;5;NESTS,111;3;4;MICE,123;3;6;TORPOR,2;2;8;DIAPAUSE,132;3;10;INACTIVITY,3;1;4;DISK,86;3;7;GRIZZLY,1;2;4;NEST,13;1;10;ESTIVATION,12;1;9;GESTATION,30;2;5;CAVES,135;0;8;AWAKENED","gridSize":12,"difficulty":"medium","wordCount":12,"wordlist":["DISK","MICE","NEST","CAVES","NESTS","TORPOR","GRIZZLY","AWAKENED","DIAPAUSE","GESTATION","ESTIVATION","INACTIVITY"]}