{"id":"12-medium-409","theme":"beach","grid":"ZMRUOBRAHZPNIQSWIMMINGUHNKTCIDLQOYZALWSRLUDTKNZNAUROYNTIOALDNYWSREODGSEBDTFMISTERXUATVOLLEYBALLLTOURISTTACYLSGZPICNICIEVFISHINGPNYVZRNBOULEVARDF","solution":"85;0;10;VOLLEYBALL,14;0;8;SWIMMING,29;1;5;DUNES,120;0;7;FISHING,111;0;6;PICNIC,96;0;7;TOURIST,2;0;7;HARBOUR,12;1;6;INLAND,23;1;8;HANDBALL,134;0;9;BOULEVARD,10;1;6;PUZZLE,43;1;4;TIDE","gridSize":12,"difficulty":"medium","wordCount":12,"wordlist":["TIDE","DUNES","INLAND","PICNIC","PUZZLE","FISHING","HARBOUR","TOURIST","HANDBALL","SWIMMING","BOULEVARD","VOLLEYBALL"]}