{"id":"12-medium-417","theme":"beach","grid":"GQCLIFFSMYORTOURISTZZYRLYXBXSOOTTGWSBIOIOKCDUNESPBUKCGEFXVLFOXLMCHARAAZXNOEEEANWTNCACHVPRRSSPALMSOASPBAWNMJVCQRZYOYLDUOVHUDGCRLDINSHSWIMMINGZURF","solution":"92;0;4;PALM,108;3;4;COVE,43;0;5;DUNES,12;0;7;TOURIST,65;1;6;HARBOR,28;1;6;SOCCER,132;0;8;SWIMMING,124;3;7;COASTAL,2;0;6;CLIFFS,26;1;9;BOULEVARD,79;3;5;WAVES,30;1;5;OCEAN","gridSize":12,"difficulty":"medium","wordCount":12,"wordlist":["COVE","PALM","DUNES","OCEAN","WAVES","CLIFFS","HARBOR","SOCCER","COASTAL","TOURIST","SWIMMING","BOULEVARD"]}