{"id":"12-medium-448","theme":"beach","grid":"ARECREATIONESHOREPLZAJSAEBZLGXINPUIFLRLXZEOEOSEIVNODOTNHRUJSBEVSYMTTIDEHUWIAIHRIPFNIYPDZGOENAMWNSOAIYVNLLFPGFRLEOOBAMBMWBTOCQRVNHXEDVRMNAQEDNVOC","solution":"17;2;4;PIER,123;3;4;COVE,49;1;7;NEWPORT,1;0;10;RECREATION,12;0;5;SHORE,79;1;6;INLAND,67;0;4;TIDE,24;2;7;EROSION,86;3;7;DAYTONA,35;1;7;FISHING,80;1;4;PALM,110;3;10;LIGHTHOUSE","gridSize":12,"difficulty":"medium","wordCount":12,"wordlist":["COVE","PALM","PIER","TIDE","SHORE","INLAND","DAYTONA","EROSION","FISHING","NEWPORT","LIGHTHOUSE","RECREATION"]}