{"id":"12-medium-701","theme":"biography","grid":"FTDPERHXYXXBNDTEUSIAVMHDSTJBSBSSZTVZHWCEWCLASPOGVRSZNRRIYQLSWIDRTTLISSUUETKCIAIQBHMXTTZQNONTTEELHEERPUMGLESDWNUYUEREOEWOBOOKTQHHMQDOJDICTIONARYP","solution":"3;2;9;PUBLISHED,2;2;9;DESCRIBES,39;2;8;ENTITLED,34;1;7;VOLUMES,132;3;10;JOURNALIST,36;3;4;HTTP,4;2;6;ESSAYS,50;2;7;MEMOIRS,37;1;7;WRITTEN,133;0;10;DICTIONARY,120;0;4;BOOK,64;2;4;TANG","gridSize":12,"difficulty":"medium","wordCount":12,"wordlist":["BOOK","HTTP","TANG","ESSAYS","MEMOIRS","VOLUMES","WRITTEN","ENTITLED","DESCRIBES","PUBLISHED","DICTIONARY","JOURNALIST"]}