{"id":"12-medium-705","theme":"rock","grid":"MUJMRGRGWRJSUAQBEQNYTTOOIKJNAIYSKWENJNRZLSIYTPMGYEFLBRSOOHMWSDOLALNITOURFRRTUXUYSASIMOIUXEHESTITRURNMRNSSNCEGAJMDMRCVXIRCYNZAIEAEOAWMKSYFTERTSNP","solution":"86;2;5;INDIE,72;2;6;FORMAT,108;3;9;GUITARIST,73;3;7;ROLLING,61;2;7;DRUMMER,15;2;7;BASSIST,60;3;6;GENRES,24;2;10;INFLUENCES,101;3;6;RHYTHM,52;2;5;BLUES,11;1;10;SONGWRITER,58;1;8;MUSICIAN","gridSize":12,"difficulty":"medium","wordCount":12,"wordlist":["BLUES","INDIE","FORMAT","GENRES","RHYTHM","BASSIST","DRUMMER","ROLLING","MUSICIAN","GUITARIST","INFLUENCES","SONGWRITER"]}