{"id":"12-medium-712","theme":"plaid","grid":"JGBGHZDOUITKCPXGSTHRSFABENRNWHSNXXRGDYDEGIATLFTWEVANSELWRLAAEQECJIQLLINREPYKKEDIIIHHBEQSWHWITATSQEHDZAAENOMNTROUSERSLGUSWFKSZJPCOSUXOHFFZJTJYQOC","solution":"127;3;5;CLOTH,114;3;6;RETINA,90;1;4;WARP,108;0;8;TROUSERS,13;2;9;PRESIDING,76;3;4;KILT,28;2;8;WILLIAMS,16;2;5;SHAWL,64;3;5;JEANS,30;2;6;SHIRTS,10;1;6;TARTAN,48;0;5;EVANS","gridSize":12,"difficulty":"medium","wordCount":12,"wordlist":["KILT","WARP","CLOTH","EVANS","JEANS","SHAWL","RETINA","SHIRTS","TARTAN","TROUSERS","WILLIAMS","PRESIDING"]}