{"id":"12-medium-841","theme":"falcon","grid":"TSPANTARCTICPPTOXGGWJWMIEAEUWDUQIGOZNCERAEGTTXTXXERLERRTPTSCUCTOBGTEORZOFRRICARCDCCNRAKCOKSISTAJEFLBLJEUNDWRKTSCJSRTEEYDBSSJOOYSYRPMMVHZHKGUZEPL","solution":"127;3;5;SEDAN,38;2;8;REUSABLE,13;2;9;PEREGRINE,1;1;10;SPACECRAFT,136;3;5;HORUS,1;2;6;STUART,90;3;5;SCOTT,72;2;5;FALCO,2;2;7;POWERED,50;2;6;ROCKET,3;0;9;ANTARCTIC","gridSize":12,"difficulty":"medium","wordCount":11,"wordlist":["FALCO","HORUS","SCOTT","SEDAN","ROCKET","STUART","POWERED","REUSABLE","ANTARCTIC","PEREGRINE","SPACECRAFT"]}