{"id":"12-medium-86","theme":"vehicle","grid":"NEAUTOMOTIVEOAMPLATESQYHIURIRAVTSNCPSTROSOAPEPRENOVECSTVCWHMEMOEAKIOETLHPOTNHREOTTYZSBZUDIYTNYEWUIZPCCCARSPXSLVBJIELXVQEPEDTCNBFEUVCNPKJUHYSXSXZ","solution":"26;2;6;ROCKET,1;2;9;EMISSIONS,13;1;10;AUTOMOBILE,15;2;9;PROTOTYPE,75;3;4;NASA,88;3;6;DRIVEN,38;2;4;REAR,0;1;10;SUSPENSION,2;0;10;AUTOMOTIVE,50;2;8;VEHICLES,15;0;6;PLATES,102;0;4;CARS","gridSize":12,"difficulty":"medium","wordCount":12,"wordlist":["CARS","NASA","REAR","DRIVEN","PLATES","ROCKET","VEHICLES","EMISSIONS","PROTOTYPE","AUTOMOBILE","AUTOMOTIVE","SUSPENSION"]}