{"id":"12-medium-926","theme":"enchanted","grid":"FAIRIESSVOSZSKCIEESMKETAHDIDLEAERNJTCMAACGGUEKUTNLTNIATMSIMRBNICTAEHRODAORATESRGLILCPLORUBLUNTOTYCCMUDONQDYIRWANDERERAQOBEVENINGAEDNSCENICLMBJGT","solution":"110;3;9;AMUSEMENT,98;3;9;CREATURES,85;3;7;MAGICAL,97;3;7;COTTAGE,50;3;5;TALES,109;0;8;WANDERER,84;3;8;PRINCESS,60;3;5;BLADE,121;0;7;EVENING,132;0;6;SCENIC,23;1;10;ATTRACTION,0;0;7;FAIRIES","gridSize":12,"difficulty":"medium","wordCount":12,"wordlist":["BLADE","TALES","SCENIC","COTTAGE","EVENING","FAIRIES","MAGICAL","PRINCESS","WANDERER","AMUSEMENT","CREATURES","ATTRACTION"]}