{"id":"12-hard-1062","theme":"beach","grid":"ANOTYADWFATBMDCCIJHTYNIEPQQIHIOOYODADIFGZNTUIIECLBCPSNERJSPHNLFNHPLIBOBEGEAGIASSRRASOMWBNCRTPEYFGCFPDNGBYCCJEGEFONNJOJTSYRTAWRAOQUBFUHGKNWTHBYRT","solution":"70;1;3;BAY,64;2;7;HARBOUR,93;5;7;EROSION,89;6;6;PICNIC,78;5;6;HOTELS,6;4;7;DAYTONA,48;2;8;HANDBALL,19;1;7;TOURIST,84;2;5;OCEAN,83;5;7;BEACHES,60;2;7;NEWPORT,10;1;4;TIDE","gridSize":12,"difficulty":"hard","wordCount":12,"wordlist":["BAY","TIDE","OCEAN","HOTELS","PICNIC","BEACHES","DAYTONA","EROSION","HARBOUR","NEWPORT","TOURIST","HANDBALL"]}