{"id":"12-hard-1118","theme":"beach","grid":"TBSLLVAPTNIBZOULLOVNAMPPSUBAAEFCKLIKLLGBBSROZEMPEENYDDAORTPITVIENPEWSSSBOAMLANVOSICDHRMLHFOCJROZJDIOLGCAEUANKFWVMIAMIOWNCYSASQJEOTOXRECREATIONPB","solution":"29;2;7;EROSION,141;4;10;RECREATION,102;5;4;COVE,111;5;10;VOLLEYBALL,24;1;6;HOTELS,88;5;8;HANDBALL,112;0;5;MIAMI,1;1;9;BOULEVARD,129;5;7;TOURIST,23;7;4;PIER,7;2;4;PALM,122;5;8;SWIMMING","gridSize":12,"difficulty":"hard","wordCount":12,"wordlist":["COVE","PALM","PIER","MIAMI","HOTELS","EROSION","TOURIST","HANDBALL","SWIMMING","BOULEVARD","RECREATION","VOLLEYBALL"]}