{"id":"12-hard-1157","theme":"beach","grid":"BXFERLECFELNQKDSEDITDPHOTAGUPIERRJVIKUFOGVDPAFTTNUDHRLMIVNOATTPTEARCEWUNRRZHCTXNLPRIOETGCSPIUEITPVZIOAACOSSSWOPLSOHUBTTEECOVZCCLGAJDNPBHARBOURQH","solution":"125;5;7;COASTAL,3;1;10;LIGHTHOUSE,118;5;7;TOURIST,11;1;11;DESTINATION,135;0;7;HARBOUR,112;5;6;SOCCER,28;0;4;PIER,43;1;6;PICNIC,60;1;7;NEWPORT,116;5;9;BOULEVARD,19;4;4;TIDE,121;5;4;COVE","gridSize":12,"difficulty":"hard","wordCount":12,"wordlist":["COVE","PIER","TIDE","PICNIC","SOCCER","COASTAL","HARBOUR","NEWPORT","TOURIST","BOULEVARD","LIGHTHOUSE","DESTINATION"]}