{"id":"12-hard-1232","theme":"sandstorm","grid":"RYSRXOYVYCCXHWTTPLHMGGDUFGNIRETSAMPZIIRELEGWEDWLSMGKDIAAOOEBZOFHLIBMSGOGJNMITWSIIUUJHSINNIFDSNSWUTTLYLNBAIGOFENTJDAGJOVJMRFORCINGNRXJVPCWGADDPTB","solution":"118;6;10;VISIBILITY,2;2;9;STREAMING,33;4;9;MASTERING,39;2;9;BROADSIDE,115;6;8;FIGHTING,90;4;7;FINNISH,62;2;7;FINLAND,122;0;7;FORCING,121;5;7;MONSTER,16;2;7;PEGASUS","gridSize":12,"difficulty":"hard","wordCount":10,"wordlist":["FINLAND","FINNISH","FORCING","MONSTER","PEGASUS","FIGHTING","BROADSIDE","MASTERING","STREAMING","VISIBILITY"]}