{"id":"12-hard-126","theme":"salad","grid":"GNISSERDZWEKHYBTEZESKZGOWDVNICSASJGAAESEVRINTNARLSHMOEADZBHESSRIHZNWRRABEEEDCINIEXBMLRDNNTOCIXPUOTDOAEYHGOBCCSECKPAEVVZUNTDFXPMSFYZCKKDMDAKRCCMN","solution":"127;5;10;SANDWICHES,126;5;10;MAYONNAISE,137;5;9;APPETIZER,100;5;9;ANCHOVIES,111;5;9;CONDIMENT,7;4;8;DRESSING,122;5;8;SHREDDED,109;5;8;DESSERTS,108;5;8;COLESLAW,131;5;8;CUCUMBER","gridSize":12,"difficulty":"hard","wordCount":10,"wordlist":["COLESLAW","CUCUMBER","DESSERTS","DRESSING","SHREDDED","ANCHOVIES","APPETIZER","CONDIMENT","MAYONNAISE","SANDWICHES"]}