{"id":"12-hard-1309","theme":"beach","grid":"UEOQJITAANAAUFLANDINGERISCBBPIERXWUILXDNXTWUPPOEELAIZJONTOBTTRPLMPJUERRCOEPLRVYBRTALHVAIMAIMOIHIUPBJZYAEXYSOJJSHOREBXHSTPICNICEEEBUZYBAYYPXNQQLV","solution":"97;3;4;PALM,118;6;4;BOYS,14;0;7;LANDING,114;4;5;SHORE,9;1;7;NEWPORT,120;0;6;PICNIC,28;0;4;PIER,41;2;7;TOURIST,22;1;7;HARBOUR,84;5;6;HOTELS,135;4;3;BAY,91;4;5;MIAMI","gridSize":12,"difficulty":"hard","wordCount":12,"wordlist":["BAY","BOYS","PALM","PIER","MIAMI","SHORE","HOTELS","PICNIC","HARBOUR","LANDING","NEWPORT","TOURIST"]}