{"id":"12-hard-1320","theme":"honesty","grid":"ZSVMTETTYQDJTSTAFUPJTXUYNAWILZTPIUETEFFICIENCYCIMDEDICATIONRTTAGBJUTLIEEIKAASIWNPVGCMYBKJXHZMAINMFRQCZVIIHLIODEALINGSAISCINTEGRITYDEPGLANOITOMEV","solution":"58;4;10;DEDICATION,45;4;10;EFFICIENCY,116;5;10;SIMPLICITY,120;5;10;COMMITMENT,119;5;9;SINCERITY,130;5;9;DILIGENCE,121;0;9;INTEGRITY,142;4;9;EMOTIONAL,109;0;8;DEALINGS","gridSize":12,"difficulty":"hard","wordCount":9,"wordlist":["DEALINGS","DILIGENCE","EMOTIONAL","INTEGRITY","SINCERITY","COMMITMENT","DEDICATION","EFFICIENCY","SIMPLICITY"]}