{"id":"12-hard-1403","theme":"harmonic","grid":"QNDSNOITCNUFKEOEQFPXDLDXNRCITEMHTIRAOOONTNZZPBNLNYITAREZEQCALVATANOMOAUCIDQWALOTGGZINYVZVLLSSUTRECWINMUISIAEABNNZCNDCIDHRMNQHNPFOSDPSLAVRETNIMOS","solution":"25;2;10;OSCILLATOR,130;6;10;DISSONANCE,1;2;10;DISTORTION,35;4;10;ARITHMETIC,141;6;10;MODULATION,2;2;9;AUGMENTED,24;1;9;NONLINEAR,140;4;9;INTERVALS,11;4;9;FUNCTIONS,143;5;9;SPHERICAL","gridSize":12,"difficulty":"hard","wordCount":10,"wordlist":["AUGMENTED","FUNCTIONS","INTERVALS","NONLINEAR","SPHERICAL","ARITHMETIC","DISSONANCE","DISTORTION","MODULATION","OSCILLATOR"]}