{"id":"12-hard-1433","theme":"dunes","grid":"WJENOTSDNASKTWETLANDSVSHLAKESHORESIRENNOITATEGEVCOASTLINETVPEVRESERPATMIJMTBKEZWNIWCECDTDLHXIGCTURALPSRHSXLMHZIDELNPBAMLIWJRFJOXDWAMZDFBDNALDOOW","solution":"134;3;10;FRESHWATER,121;3;10;WILDERNESS,47;4;10;VEGETATION,48;0;9;COASTLINE,24;0;9;LAKESHORE,10;4;9;SANDSTONE,20;4;8;WETLANDS,60;0;8;PRESERVE,143;4;8;WOODLAND","gridSize":12,"difficulty":"hard","wordCount":9,"wordlist":["PRESERVE","WETLANDS","WOODLAND","COASTLINE","LAKESHORE","SANDSTONE","FRESHWATER","VEGETATION","WILDERNESS"]}