{"id":"12-hard-1477","theme":"beach","grid":"ABWDBAYDYVJTABOULEVARDJHJVOLLEYBALLANNOITANITSEDSSCAKYUSRQGEFWOAPSFMEFJYFIANEROIIVPPIMSOQSOCCERVLMTTCINCIPRVCIAYHGNIDNALCNLACHOTELSGVGUDJDPIKRAW","solution":"119;4;7;LANDING,108;5;6;CLIFFS,47;4;11;DESTINATION,130;4;6;HOTELS,122;5;7;COASTAL,135;5;7;DAYTONA,89;0;6;SOCCER,6;4;3;BAY,21;4;9;BOULEVARD,25;0;10;VOLLEYBALL,49;1;8;SWIMMING,105;4;6;PICNIC","gridSize":12,"difficulty":"hard","wordCount":12,"wordlist":["BAY","CLIFFS","HOTELS","PICNIC","SOCCER","COASTAL","DAYTONA","LANDING","SWIMMING","BOULEVARD","VOLLEYBALL","DESTINATION"]}