{"id":"12-hard-1644","theme":"beach","grid":"NLLABYELLOVSILSXPKVDJMEHQGNIMMIWSAACHARBOURDDHDARDCXQPIIYERLCLZRRYROSSAITLWRPOVCEYVFEOIALRXEMOEOGKYFVCOAIBLRZQBWFELNARUNDMWNXSSGMTOISEHCAEBQIABA","solution":"35;1;10;CALIFORNIA,67;1;5;OCEAN,142;5;9;BOULEVARD,25;0;8;SWIMMING,60;2;6;CLIFFS,105;5;4;BOYS,138;4;7;BEACHES,99;3;7;FLORIDA,10;4;10;VOLLEYBALL,74;2;5;WAVES,42;4;7;HARBOUR,92;1;5;MIAMI","gridSize":12,"difficulty":"hard","wordCount":12,"wordlist":["BOYS","MIAMI","OCEAN","WAVES","CLIFFS","BEACHES","FLORIDA","HARBOUR","SWIMMING","BOULEVARD","CALIFORNIA","VOLLEYBALL"]}