{"id":"12-hard-1678","theme":"software","grid":"NOITALUMISGAXNOITAMOTUATCOMPATIBLEHPJMSNOITULOSREHSOTNICAMDWCOMPUTINGSHFPTFOSORCIMPCREDIVORPJFSVGNILEDOMCNTUDEDDEBMEROIBYOBFDXUFMNAKWYJQLRODQAOQ","solution":"22;4;10;AUTOMATION,9;4;10;SIMULATION,24;0;10;COMPATIBLE,46;4;9;SOLUTIONS,57;4;9;MACINTOSH,68;4;9;COMPUTING,73;0;9;MICROSOFT,91;4;8;PROVIDER,103;4;8;MODELING,115;4;8;EMBEDDED","gridSize":12,"difficulty":"hard","wordCount":10,"wordlist":["EMBEDDED","MODELING","PROVIDER","COMPUTING","MACINTOSH","MICROSOFT","SOLUTIONS","AUTOMATION","COMPATIBLE","SIMULATION"]}