{"id":"12-hard-1700","theme":"beach","grid":"TVLDARKWLHPDLONCLIFFSRTRLHULLSNAECOSAINROFILACMEBSEWISIUGIRVYYUVKSXPJDVAELETOMTTCCZWLUKTHCDFVPQOLPQDRAVELUOBOENOITAERCERVHHLATSAOCWFTIDEHANDBALL","solution":"50;2;4;COVE,36;0;10;CALIFORNIA,136;0;8;HANDBALL,120;5;10;VOLLEYBALL,119;4;10;RECREATION,0;2;7;TOURIST,123;0;7;COASTAL,107;4;9;BOULEVARD,15;0;6;CLIFFS,34;4;5;OCEAN,132;0;4;TIDE,35;1;5;WAVES","gridSize":12,"difficulty":"hard","wordCount":12,"wordlist":["COVE","TIDE","OCEAN","WAVES","CLIFFS","COASTAL","TOURIST","HANDBALL","BOULEVARD","CALIFORNIA","RECREATION","VOLLEYBALL"]}