{"id":"12-hard-1714","theme":"beach","grid":"RECREATIONLYCIMAIMEDDPIMCEYGCULJRVGPMFLORIDAAZHTWQJTEXLVVDTOWBIBETLREEHZSDGGVRAOLQOCEELSOOBBUQULAKVCCPDROISCSMEAIWNABVECGANZWEAHCHXANNZGYNHKBBKC","solution":"124;6;5;WAVES,10;1;10;LIGHTHOUSE,65;1;7;NEWPORT,67;1;6;HARBOR,43;4;7;FLORIDA,116;5;9;BOULEVARD,138;5;8;HANDBALL,13;0;5;MIAMI,88;7;5;OCEAN,0;0;10;RECREATION,100;5;4;COVE,51;7;4;TIDE","gridSize":12,"difficulty":"hard","wordCount":12,"wordlist":["COVE","TIDE","MIAMI","OCEAN","WAVES","HARBOR","FLORIDA","NEWPORT","HANDBALL","BOULEVARD","LIGHTHOUSE","RECREATION"]}