{"id":"12-hard-1900","theme":"beach","grid":"RRMDQQEMPXXCTEDNALNIRAAOFCVAVPEUOLFNLCBOOROPIFIYOORRLBEFMTSNRSURRLOOVHHAIBXAIRESCKIEDXHTNEJYEENCAEAIBSMMBNGOJYAAYGTXXAUEMCOVENCFNHLDKUNNEWPORTGL","solution":"143;6;10;VOLLEYBALL,11;7;10;CALIFORNIA,24;1;7;FLORIDA,121;0;4;COVE,61;5;6;SOCCER,106;5;7;FISHING,131;6;5;DUNES,135;0;7;NEWPORT,8;7;4;PIER,86;3;7;HARBOUR,107;5;5;OCEAN,19;4;6;INLAND","gridSize":12,"difficulty":"hard","wordCount":12,"wordlist":["COVE","PIER","DUNES","OCEAN","INLAND","SOCCER","FISHING","FLORIDA","HARBOUR","NEWPORT","CALIFORNIA","VOLLEYBALL"]}