{"id":"12-hard-1911","theme":"herbs","grid":"CMHDCBMYNWYKCSXHYXROOSSMCTEQAAFPGMEACHCNMJLOAOLRRTAEIJAPROBOZISMOCNFRRAJHOOGOKIAAHTRRXIPSMCDTSEAAROMATICEUGMGUEOGKDLBMERCIMAYREUELVNGUBOGLMLFSJA","solution":"130;5;10;VEGETABLES,117;5;9;MUSHROOMS,117;6;9;MEDICINES,24;2;9;CHAMOMILE,138;5;9;MEDICINAL,92;5;8;TARRAGON,7;7;8;ROSEMARY,96;0;8;AROMATIC,107;5;8;MARJORAM","gridSize":12,"difficulty":"hard","wordCount":9,"wordlist":["AROMATIC","MARJORAM","ROSEMARY","TARRAGON","CHAMOMILE","MEDICINAL","MEDICINES","MUSHROOMS","VEGETABLES"]}