{"id":"12-hard-2003","theme":"beach","grid":"NISXJDHTRLTSOEBXQZLSUGIDISQNZUAIONDWTUVOWQNRBIEEAOVIHBDURMDMEHYSYCIOAMKRRTEOOINTHIFECHVRPNGTJWSIEGAEDZTUCSZPRIRLLABDNAHKJLRXKCINCIPZNSEVAWXHXYDF","solution":"10;1;4;TIDE,79;5;7;TOURIST,121;5;10;LIGHTHOUSE,111;0;8;HANDBALL,107;5;4;PIER,108;5;10;RECREATION,105;5;8;SWIMMING,27;1;7;EROSION,18;1;7;LANDING,8;1;7;HARBOUR,137;4;5;WAVES,125;0;6;PICNIC","gridSize":12,"difficulty":"hard","wordCount":12,"wordlist":["PIER","TIDE","WAVES","PICNIC","EROSION","HARBOUR","LANDING","TOURIST","HANDBALL","SWIMMING","LIGHTHOUSE","RECREATION"]}