{"id":"12-hard-2041","theme":"beach","grid":"AOJNVRCQLKBGCNFZEICRIOGXOEGINYBIULZVCZICSAALBIBIECIMVHEBKGESAPSEAVIGNHALNJBQAIGNBTCEFATRGFMIGHHTYLDWRPYDCOEOSOPEMASNKUSHAGIMBLYABSQXRPOXJMULYEDV","solution":"137;5;4;PALM,10;7;9;BOULEVARD,14;2;7;FISHING,6;7;6;PICNIC,59;1;6;HOTELS,133;3;4;PIER,24;1;5;OCEAN,139;5;7;LANDING,141;5;10;LIGHTHOUSE,74;7;3;BAY,90;6;5;MIAMI,46;1;7;BEACHES","gridSize":12,"difficulty":"hard","wordCount":12,"wordlist":["BAY","PALM","PIER","MIAMI","OCEAN","HOTELS","PICNIC","BEACHES","FISHING","LANDING","BOULEVARD","LIGHTHOUSE"]}