{"id":"12-hard-2064","theme":"beach","grid":"NOITANITSEDLHRZMCOVEDIQLYOVPCWSQHTLAFMARAMESAALBWWNGLXHGRIAYQFONIPCVBJBEDITOFLAJOXDLUSYIOKEBRUNLNHASRKBJTIAOEIDONPDVEEHVSNWRIADIROLFBGWEAUKEDCKF","solution":"102;5;7;BEACHES,32;1;6;HARBOR,120;5;5;DUNES,10;4;11;DESTINATION,135;5;7;EROSION,16;0;4;COVE,11;1;10;VOLLEYBALL,110;5;7;DAYTONA,133;5;7;FISHING,125;0;7;FLORIDA,28;1;10;CALIFORNIA,118;5;8;HANDBALL","gridSize":12,"difficulty":"hard","wordCount":12,"wordlist":["COVE","DUNES","HARBOR","BEACHES","DAYTONA","EROSION","FISHING","FLORIDA","HANDBALL","CALIFORNIA","VOLLEYBALL","DESTINATION"]}