{"id":"12-hard-2201","theme":"organic","grid":"HSDNUOPMOCXIUSECNATSBUSTGDESLDIZSZVXVTODCBZBUNLILREZILITREFNANKPKCVTOSXOCJRCHMIMHMCRIFFHHJVTPONGMOLECULESLPAERWWUXWEOEHNHJEDIROLHCPICFEHDAXSPRSC","solution":"140;5;10;PHOSPHORUS,49;0;10;FERTILIZER,130;6;10;PESTICIDES,22;4;10;SUBSTANCES,9;4;9;COMPOUNDS,96;0;9;MOLECULES,47;1;9;INORGANIC,48;1;8;CHEMICAL,129;4;8;CHLORIDE","gridSize":12,"difficulty":"hard","wordCount":9,"wordlist":["CHEMICAL","CHLORIDE","COMPOUNDS","INORGANIC","MOLECULES","FERTILIZER","PESTICIDES","PHOSPHORUS","SUBSTANCES"]}