{"id":"12-hard-2346","theme":"snack","grid":"ERZWHFBDBKCZPTRESSEDGUQPCWDEROVALFHATLFTNEIRTUNQQTRTSREKCARCUXKALLITROTPRSEGAREVEBXADYSEHCIWDNASISELBATEGEVGBISCUITSFNUESELDOONTNNIDXFHYORYQEYDD","solution":"95;4;10;SANDWICHES,106;4;10;VEGETABLES,81;4;9;BEVERAGES,70;4;8;TORTILLA,59;4;8;CRACKERS,46;4;8;NUTRIENT,115;4;8;BISCUITS,33;4;8;FLAVORED,19;4;7;DESSERT,126;4;7;NOODLES","gridSize":12,"difficulty":"hard","wordCount":10,"wordlist":["DESSERT","NOODLES","BISCUITS","CRACKERS","FLAVORED","NUTRIENT","TORTILLA","BEVERAGES","SANDWICHES","VEGETABLES"]}