{"id":"12-hard-2379","theme":"beach","grid":"HQRDCUUATRMSSEHCAEBMPICLANSWIMMINGMEXQSWAVESYOBTNAWTCOBOOHGOAYMREGNEKMNHJZLWEEEVOCTYUGAAWSPICNICEGPPXHMRGWYYDXOVICAXRAHARROCEANMBAKDTUSFFILCSYRT","solution":"46;4;4;BOYS,43;4;5;WAVES,126;4;5;OCEAN,90;0;6;PICNIC,132;3;7;NEWPORT,26;0;8;SWIMMING,98;5;4;PALM,18;4;7;BEACHES,134;0;6;CLIFFS,81;4;4;COVE,71;5;6;HOTELS,128;3;3;BAY","gridSize":12,"difficulty":"hard","wordCount":12,"wordlist":["BAY","BOYS","COVE","PALM","OCEAN","WAVES","CLIFFS","HOTELS","PICNIC","BEACHES","NEWPORT","SWIMMING"]}