{"id":"12-hard-2397","theme":"beach","grid":"SVSICGYWSVYAELCYNNRMWTKNHJOKOIHEHBLOCZAEIMXBIUEIACSGSMYHUPVTEITTOIOOLJOABNALRWGMANCNMCLNESEXZYBIMIWROBRAHACTXPLLABDNAHTSDESUOHTHGILEOGAINLANDGBD","solution":"57;6;4;PIER,99;0;6;HARBOR,110;0;8;HANDBALL,89;5;8;SWIMMING,143;5;11;DESTINATION,14;1;7;COASTAL,16;1;7;EROSION,130;4;10;LIGHTHOUSE,0;1;7;BEACHES,82;5;4;COVE,135;0;6;INLAND,109;5;6;PICNIC","gridSize":12,"difficulty":"hard","wordCount":12,"wordlist":["COVE","PIER","HARBOR","INLAND","PICNIC","BEACHES","COASTAL","EROSION","HANDBALL","SWIMMING","LIGHTHOUSE","DESTINATION"]}