{"id":"12-hard-2531","theme":"gadget","grid":"NAGASAKIJKOGOTVANIMATEDNISAVHTRINITYTUEDUFQKMOIPADDRVYMKQNJBMOFFUEEUVFFHIUNOITNEVNICNPRESENTERVLAWWOJTXEUZGXOJBROENOVRGISCYRHCPNLDENHDESKTOPUMAX","solution":"142;6;10;ADVENTURES,26;2;9;ADVENTURE,85;0;9;PRESENTER,82;4;9;INVENTION,96;5;9;ANIMATION,46;7;8;INVENTOR,0;0;8;NAGASAKI,22;4;8;ANIMATED,35;4;7;TRINITY,139;4;7;DESKTOP","gridSize":12,"difficulty":"hard","wordCount":10,"wordlist":["DESKTOP","TRINITY","ANIMATED","INVENTOR","NAGASAKI","ADVENTURE","ANIMATION","INVENTION","PRESENTER","ADVENTURES"]}