{"id":"12-hard-2601","theme":"beach","grid":"XKBEACHESZAOKSRVOAEPYGXFUAROSVEROHSMASNVBEROSIONKFXOMRNVDKHZCALLTMAURPAFPIAOCYAHDPRONPNORLABPIBJTTDCPIIDOEOHKYONIQDFORUJOQKDQPNAFPRWLHMYCKIIJSNF","solution":"85;3;4;PALM,41;0;7;EROSION,76;2;6;CLIFFS,34;4;5;SHORE,25;2;7;DAYTONA,49;2;7;FLORIDA,28;2;5;DUNES,14;2;6;HARBOR,125;6;6;PICNIC,2;0;7;BEACHES,117;5;4;PIER,58;1;7;HARBOUR","gridSize":12,"difficulty":"hard","wordCount":12,"wordlist":["PALM","PIER","DUNES","SHORE","CLIFFS","HARBOR","PICNIC","BEACHES","DAYTONA","EROSION","FLORIDA","HARBOUR"]}