{"id":"12-hard-2624","theme":"crater","grid":"QKETIROETEMZCLINCINACLOVHOULCRGWTGJTENPSOEWDRXXJMGVEEMLDFACKIIQOROEAGKCESTJGUNNTDZYUPUDKPOIAEUHVHDYBTRWCCRSYEEGOITGPULSNRDLNOSGLGSOUEVNTNABZLYEV","solution":"1;2;10;KILOMETERS,129;6;10;COPERNICUS,29;1;10;ASTRONOMER,24;1;10;HEMISPHERE,143;6;9;VOLCANOES,2;2;9;ENCELADUS,10;4;9;METEORITE,13;1;9;LONGITUDE,23;4;8;VOLCANIC,52;1;8;ERUPTION","gridSize":12,"difficulty":"hard","wordCount":10,"wordlist":["ERUPTION","VOLCANIC","ENCELADUS","LONGITUDE","METEORITE","VOLCANOES","ASTRONOMER","COPERNICUS","HEMISPHERE","KILOMETERS"]}