{"id":"12-hard-2692","theme":"zebra","grid":"YLFRETTUBFLETSQSTALLIONLSSOASTFWFMMUUEEREECVVXVDAAIEEVISAVNINEMCBCKZKDCETIBTEEOIPIHDEKBETPDNVLPDLVNWRFSLIYAFOQONAENBIHOAPMXIHNMGUWROEKOBGNIRPSDF","solution":"130;6;10;RHINOCEROS,129;6;10;WILDEBEEST,24;2;10;SUBSPECIES,16;1;10;HARTEBEEST,8;4;9;BUTTERFLY,141;4;9;SPRINGBOK,15;0;8;STALLION,59;4;8;INVASIVE,132;5;8;ANTELOPE","gridSize":12,"difficulty":"hard","wordCount":9,"wordlist":["ANTELOPE","INVASIVE","STALLION","BUTTERFLY","SPRINGBOK","HARTEBEEST","RHINOCEROS","SUBSPECIES","WILDEBEEST"]}