{"id":"12-hard-2943","theme":"beach","grid":"NMNAMSPDGGHSHOTSIRUOTLREKAISSNYNQLGHUNBSEPLOCLSCPORSOVGILAMASTDRJRATIBIEVYTLWSEAFYABWAEEAYJEFEMAGDDUVOFRSLIMLIJKEBMCSLZWTKSRSJZEVOUVTDPUIXMRLVWF","solution":"0;2;7;EROSION,33;1;10;VOLLEYBALL,139;5;10;RECREATION,113;5;4;BOYS,120;3;4;TIDE,97;5;7;DAYTONA,83;5;7;BEACHES,7;7;5;DUNES,106;5;5;MIAMI,44;1;6;CLIFFS,76;1;5;WAVES,20;4;7;TOURIST","gridSize":12,"difficulty":"hard","wordCount":12,"wordlist":["BOYS","TIDE","DUNES","MIAMI","WAVES","CLIFFS","BEACHES","DAYTONA","EROSION","TOURIST","RECREATION","VOLLEYBALL"]}