{"id":"12-hard-2992","theme":"birthday","grid":"ESIRPRUSNFPHCDERRETNIMOPMENTHPZMANNIPELORPASOONMYJTEIRXREOZWARUABNAFIHSMDQESRRASDKVOIGPTYBAPUYYHLJMVECETMERNOXSKCMQLEOFSHNYOGXEREDCKRADNELACKCWF","solution":"12;2;10;CELEBRATED,130;6;9;COMPANION,141;6;9;CELEBRATE,139;6;8;CEMETERY,123;3;8;OCCASION,11;7;8;HONORARY,20;4;8;INTERRED,7;4;8;SURPRISE,139;4;8;CALENDAR,120;5;7;HOLIDAY","gridSize":12,"difficulty":"hard","wordCount":10,"wordlist":["HOLIDAY","CALENDAR","CEMETERY","HONORARY","INTERRED","OCCASION","SURPRISE","CELEBRATE","COMPANION","CELEBRATED"]}