{"id":"12-hard-3031","theme":"streamer","grid":"KJVKYLGQMKDHSDDDQQMSSEVGOVETHAIZAJGQJNSUOROLAVWNGPDNOITATICKSNHRLORRAINERYRTNALLAGKWSEDORTCELEQATPHILIPPINEZLATNEMIGERXZBDISCHARGEXLETTESSACDDAG","solution":"93;4;10;ELECTRODES,106;4;10;PHILIPPINE,117;4;10;REGIMENTAL,81;4;9;GALLANTRY,96;3;9;TERRORISM,129;4;9;DISCHARGE,45;4;8;VALOROUS,58;4;8;CITATION,139;4;8;CASSETTE,71;4;8;LORRAINE","gridSize":12,"difficulty":"hard","wordCount":10,"wordlist":["CASSETTE","CITATION","LORRAINE","VALOROUS","DISCHARGE","GALLANTRY","TERRORISM","ELECTRODES","PHILIPPINE","REGIMENTAL"]}