{"id":"12-hard-3053","theme":"aircraft","grid":"ENILRIAEFEVZDONUGMGANPEGUXCDJALARCRNTRUFLTLOAEJCQJVEIPTPTTUTIJSTOOSPAMNFYUUNTOOCKKBEFDOYRCTOEEZDEMPEIIQTOAONDEALCLYGFBXDFXEALSDAFUUJFHLNORDAUQSQ","solution":"34;7;10;HELICOPTER,22;7;9;AEROSPACE,97;3;9;MONOPLANE,21;7;9;PROTOTYPE,84;3;8;FUSELAGE,96;3;8;ALTITUDE,142;4;8;SQUADRON,57;7;8;TACTICAL,56;1;7;TAKEOFF,6;4;7;AIRLINE","gridSize":12,"difficulty":"hard","wordCount":10,"wordlist":["AIRLINE","TAKEOFF","ALTITUDE","FUSELAGE","SQUADRON","TACTICAL","AEROSPACE","MONOPLANE","PROTOTYPE","HELICOPTER"]}