{"id":"12-hard-3228","theme":"beach","grid":"NXIKDXPQMBQMEDSEXARIUFLKWCVDNNENEAWIPSXROVCSPRAMOWAAIBROJYVPRINVSUECDUEWTMOEOQACSYSDYMTLRXTEUXUGMIYUEFIRMNCKVNAOOXOGEXDUGGDBERNSBWMNXBYHROBRAHLT","solution":"141;4;6;HARBOR,83;7;5;DUNES,28;1;7;EROSION,121;5;8;SWIMMING,18;1;10;RECREATION,72;5;7;NEWPORT,43;1;6;SOCCER,6;2;4;PIER,50;1;7;DAYTONA,123;5;9;BOULEVARD,34;1;5;WAVES,44;3;4;PALM","gridSize":12,"difficulty":"hard","wordCount":12,"wordlist":["PALM","PIER","DUNES","WAVES","HARBOR","SOCCER","DAYTONA","EROSION","NEWPORT","SWIMMING","BOULEVARD","RECREATION"]}