{"id":"12-hard-389","theme":"marina","grid":"ERUSAELPRSVDRFRJGYLGINJFETFJNDJNONNBSNDCIRGIVISJTOFXPAETRDCVARFIPVMAEHAQUFGOOEIOSYWJRRRNHLRLECJNAEVXSUAFRRYCNTIGMOTUDQQCTAQVCBEQGXAJNWBXFISHINGJ","solution":"133;5;10;WATERFRONT,12;1;10;RESTAURANT,9;7;9;SINGAPORE,125;5;9;BOULEVARD,104;5;9;RESERVOIR,103;5;8;FLOATING,54;1;8;EMIRATES,7;4;8;PLEASURE,100;5;8;SHOPPING,136;0;7;FISHING","gridSize":12,"difficulty":"hard","wordCount":10,"wordlist":["FISHING","EMIRATES","FLOATING","PLEASURE","SHOPPING","BOULEVARD","RESERVOIR","SINGAPORE","RESTAURANT","WATERFRONT"]}