{"id":"12-hard-466","theme":"beach","grid":"WWWMHARBOURXACNEWPORTOMFVOYWIGEICDAAENYMWRHVGBHFSIAGOSSOKTUNAIRHLCLIFFSPMCSETDELZZUPIZTPIGNIHSIFEOADDUOEBPFQHZQZEBCSSDELRECREATIONHWDIDAYTONAJMM","solution":"70;4;6;CLIFFS,76;1;4;TIDE,4;0;7;HARBOUR,20;4;7;NEWPORT,95;4;7;FISHING,108;3;6;HOTELS,72;3;5;MIAMI,134;0;7;DAYTONA,30;7;5;SHORE,120;0;10;RECREATION,48;5;5;WAVES,83;4;6;PUZZLE","gridSize":12,"difficulty":"hard","wordCount":12,"wordlist":["TIDE","MIAMI","SHORE","WAVES","CLIFFS","HOTELS","PUZZLE","DAYTONA","FISHING","HARBOUR","NEWPORT","RECREATION"]}