{"id":"12-hard-496","theme":"beach","grid":"TOURISTINYPBFKTZMMVNOGAPXNVSNIFLININZEOFHASATINOQWLFFMLNADRICPLILILDENOSGOELOCAVRAFOARYCRYBCCLIRUTBAIXDGEPLEMZAJDNNORNACUXLBAEAFSMCZMVLHRKHXRYHN","solution":"116;5;10;RECREATION,17;1;5;MIAMI,7;1;6;INLAND,27;1;6;CLIFFS,134;5;10;VOLLEYBALL,52;1;7;FLORIDA,97;5;7;NEWPORT,0;0;7;TOURIST,54;1;8;HANDBALL,107;5;7;EROSION,130;5;10;CALIFORNIA,93;5;7;LANDING","gridSize":12,"difficulty":"hard","wordCount":12,"wordlist":["MIAMI","CLIFFS","INLAND","EROSION","FLORIDA","LANDING","NEWPORT","TOURIST","HANDBALL","CALIFORNIA","RECREATION","VOLLEYBALL"]}