{"id":"12-hard-509","theme":"beach","grid":"SHOREDIVVWABRBBEACHESIACVOZLPGXINCIKGYFKIFYRPMNUFSSLCBOAAELBPNSWNFSKLRAQIEKCIMSEMWNOEFILCMPLVLDRRNAECOMKEALBGCIFCSRIVTWLFHZACSKVNEOAOQBGVJSOQGSH","solution":"10;7;10;CALIFORNIA,118;6;5;WAVES,50;2;8;SWIMMING,78;2;6;HOTELS,28;1;6;PICNIC,34;1;6;INLAND,60;1;4;PIER,44;1;4;PALM,4;4;5;SHORE,97;0;5;OCEAN,14;0;7;BEACHES,13;1;4;BOYS","gridSize":12,"difficulty":"hard","wordCount":12,"wordlist":["BOYS","PALM","PIER","OCEAN","SHORE","WAVES","HOTELS","INLAND","PICNIC","BEACHES","SWIMMING","CALIFORNIA"]}