{"id":"12-hard-760","theme":"ship","grid":"YDNUORGASQBBORBUETTLXSDMDAHWVLEDUEAUEYIULSEBSRNGPPFOSPMTIDUSRIDEPARTEDMVOHVAROIRPCPUTSRIYMWPTWGCPCNEEAYHZEXESERRYCMVCOSMRPXEYFRRZGXVEEJUCOQFBTPN","solution":"22;7;9;DESTROYER,21;7;9;SUBMARINE,62;0;8;DEPARTED,31;7;8;SCRAPPED,85;5;8;SHIPYARD,100;3;8;MARITIME,35;7;8;UNDERWAY,74;3;7;VESSELS,7;4;7;AGROUND,84;5;7;TORPEDO","gridSize":12,"difficulty":"hard","wordCount":10,"wordlist":["AGROUND","TORPEDO","VESSELS","DEPARTED","MARITIME","SCRAPPED","SHIPYARD","UNDERWAY","DESTROYER","SUBMARINE"]}