{"id":"12-hard-798","theme":"pizza","grid":"AICCACOFAGMXAIREZZIPOUZCXINOREPPEPNEPNATILOPAENRSTNARUATSERZTSANDWICHESIMOZZARELLAHOHCIWDNASEQGWXZYAWAEKATANJDEFFUTSAWFDFUYQTWGRJTGBGTAHPQPFFBTT","solution":"81;4;10;MOZZARELLA,70;4;10;SANDWICHES,58;4;10;RESTAURANT,46;4;10;NEAPOLITAN,33;4;9;PEPPERONI,19;4;8;PIZZERIA,91;4;8;SANDWICH,7;4;8;FOCACCIA,105;4;8;TAKEAWAY,115;4;7;STUFFED","gridSize":12,"difficulty":"hard","wordCount":10,"wordlist":["STUFFED","FOCACCIA","PIZZERIA","SANDWICH","TAKEAWAY","PEPPERONI","MOZZARELLA","NEAPOLITAN","RESTAURANT","SANDWICHES"]}