{"id":"12-hard-827","theme":"beach","grid":"AJINLANDALOTCTSROBRAHAJQLNHBBDEGFNFGISOBKEYIRDHVFYROOWSQIIZNFAEYCHEFBNWNSZZSIVIVOGDWWCENTOURISTWQQGSADIROLFYLDRAVELUOBMNQHESUOHTHGILXQGNIMAIMITB","solution":"81;5;7;LANDING,98;3;7;FISHING,117;4;9;BOULEVARD,14;1;5;SHORE,106;4;7;FLORIDA,131;4;10;LIGHTHOUSE,20;4;6;HARBOR,39;1;4;BOYS,140;4;5;MIAMI,94;4;7;TOURIST,12;1;6;CLIFFS,2;0;6;INLAND","gridSize":12,"difficulty":"hard","wordCount":12,"wordlist":["BOYS","MIAMI","SHORE","CLIFFS","HARBOR","INLAND","FISHING","FLORIDA","LANDING","TOURIST","BOULEVARD","LIGHTHOUSE"]}