{"id":"12-hard-904","theme":"beach","grid":"HLFLOFNKBMCDZHSEHCAEBZNNGLNRNAECOGTABJHUWYYKIAQLORAUNEWPORTNYERGUJTBRNKISIBCZCIPAJSUKPOQIIDMPYXLWMUQPTENNYCGMGRAUZROBRAHSDRAVELUOBSEHILATSAOCRHT","solution":"28;0;5;OCEAN,119;4;6;HARBOR,52;0;7;NEWPORT,66;1;4;TIDE,36;1;4;BOYS,121;0;9;BOULEVARD,20;4;7;BEACHES,71;5;6;INLAND,140;4;7;COASTAL,110;5;7;HARBOUR,49;1;4;PIER,67;2;3;BAY","gridSize":12,"difficulty":"hard","wordCount":12,"wordlist":["BAY","BOYS","PIER","TIDE","OCEAN","HARBOR","INLAND","BEACHES","COASTAL","HARBOUR","NEWPORT","BOULEVARD"]}