{"id":"12-easy-1049","theme":"beach","grid":"IJPICNICJSMUDLZLXPIERTRHVSHORERAKIIMXTTWQBDQGNADDLGPALMUVEAYUAVYLHUVKWEONNBOYSXCPPLIEDMZWAVESOJNSIIULIFTXRILKNAMDQOIGTKAKGMPBHMDFTXNCJIZEQSEYDID","solution":"88;0;5;WAVES,86;1;5;MIAMI,17;0;4;PIER,103;1;4;TIDE,45;1;7;NEWPORT,51;0;4;PALM,49;1;7;LANDING,2;0;6;PICNIC,83;1;6;INLAND,48;1;5;DUNES,25;0;5;SHORE,74;0;4;BOYS","gridSize":12,"difficulty":"easy","wordCount":12,"wordlist":["BOYS","PALM","PIER","TIDE","DUNES","MIAMI","SHORE","WAVES","INLAND","PICNIC","LANDING","NEWPORT"]}