{"id":"12-easy-1138","theme":"beach","grid":"IGXINLANDVYXPOCEANJVKEGMEROSIONUJLTWKZBCBOYSITKZTFJLCOSAAFUBYIDVONWDHFCDYSSPAGIANLLSMHMISLMYEOIODICCTGMTTRFCYNLNANIOUIFCPGCILHNNGDSEISZCQSGAUAUR","solution":"13;0;5;OCEAN,70;1;6;CLIFFS,54;1;8;SWIMMING,69;1;7;FLORIDA,3;0;6;INLAND,75;1;6;PICNIC,49;1;7;FISHING,67;1;7;DAYTONA,52;1;7;COASTAL,83;1;6;SOCCER,40;0;4;BOYS,24;0;7;EROSION","gridSize":12,"difficulty":"easy","wordCount":12,"wordlist":["BOYS","OCEAN","CLIFFS","INLAND","PICNIC","SOCCER","COASTAL","DAYTONA","EROSION","FISHING","FLORIDA","SWIMMING"]}