{"id":"12-easy-1609","theme":"beach","grid":"UHXBCEFOUXBSTCOKEROSIONOHLCOASTALPHCSMHYWLTVBMECMIAMIORYPSOERRNFLORIDAZRCTDSBOYSPIERKEBIONEWPORTAHAEADPCUHQHCULXDAYTONABINLSMYESHOREFDUNESBUNVIY","solution":"26;0;7;COASTAL,112;0;7;DAYTONA,38;1;8;HANDBALL,16;0;7;EROSION,63;0;7;FLORIDA,48;0;5;MIAMI,89;0;7;NEWPORT,127;0;5;SHORE,133;0;5;DUNES,11;1;6;SOCCER,76;0;4;BOYS,80;0;4;PIER","gridSize":12,"difficulty":"easy","wordCount":12,"wordlist":["BOYS","PIER","DUNES","MIAMI","SHORE","SOCCER","COASTAL","DAYTONA","EROSION","FLORIDA","NEWPORT","HANDBALL"]}