{"id":"12-easy-2348","theme":"beach","grid":"LHARBOURWKKPALBQNODUNESTONEWPORTMHTEFICBDAYTONAVWAOCLIFFSEXIADAFPPYMSRPPVMSFITZIDIHFESTYCJBAFGOBSSAJNQIMVRTOSZLFISHINGEYEEOCCFETOXLSEGTOHPVKPISU","solution":"95;1;4;BOYS,51;0;6;CLIFFS,82;1;6;HOTELS,25;0;7;NEWPORT,48;1;5;WAVES,67;1;5;MIAMI,64;1;6;PICNIC,1;0;7;HARBOUR,18;0;5;DUNES,40;0;7;DAYTONA,38;1;7;COASTAL,111;0;7;FISHING","gridSize":12,"difficulty":"easy","wordCount":12,"wordlist":["BOYS","DUNES","MIAMI","WAVES","CLIFFS","HOTELS","PICNIC","COASTAL","DAYTONA","FISHING","HARBOUR","NEWPORT"]}