{"id":"12-easy-2673","theme":"beach","grid":"IHBCZGCSTLMQNOEOWLOTLZJNLTAAAKVOYMSEAECSVWEUJGWWNLHTEQDRVWIPDSEASCCILQMOBYSLNCISJQMRJBQLFTCTIDITSOCCERMOWHNYMRZDFMIAMIGDEGMZACBUYKWWPXWSMBOYSPVH","solution":"6;1;4;COVE,19;1;7;TOURIST,113;0;5;MIAMI,96;0;6;SOCCER,137;0;4;BOYS,3;1;7;COASTAL,16;1;5;WAVES,2;1;7;BEACHES,1;1;6;HOTELS,23;1;7;NEWPORT,34;1;8;SWIMMING,0;1;6;INLAND","gridSize":12,"difficulty":"easy","wordCount":12,"wordlist":["BOYS","COVE","MIAMI","WAVES","HOTELS","INLAND","SOCCER","BEACHES","COASTAL","NEWPORT","TOURIST","SWIMMING"]}