{"id":"12-easy-2752","theme":"beach","grid":"EROSIONPFIBCZUURHWKIIVEOWADNYZZESPAACLIFFSWRHSCSLTMXWGHGOOHTCSLNWXEVRCEAIZDPTTRRECSLSIDUNESHPEWUESHARBORDRXYTYOMIAMIONVTCLZIQDAYTONACOVERMKHWKAL","solution":"86;0;5;DUNES,125;0;7;DAYTONA,132;0;4;COVE,36;0;6;CLIFFS,10;1;7;BEACHES,32;1;5;SHORE,11;1;7;COASTAL,111;0;5;MIAMI,7;1;4;PIER,0;0;7;EROSION,45;1;6;SOCCER,98;0;6;HARBOR","gridSize":12,"difficulty":"easy","wordCount":12,"wordlist":["COVE","PIER","DUNES","MIAMI","SHORE","CLIFFS","HARBOR","SOCCER","BEACHES","COASTAL","DAYTONA","EROSION"]}