{"id":"12-easy-899","theme":"beach","grid":"ISHOREUCOVEONLANDINGYDCULHIZCOASTALPATWQEROSIONCNQSWIMMINGJDDKNEWPORTTKXDNHSTOURISTKCIHARBOUREMNRZDKJNVOHMNSHFMMIFISHINGIXERIIKETZQFKIAKITPIEROU","solution":"76;0;7;TOURIST,138;0;4;PIER,62;0;7;NEWPORT,86;0;7;HARBOUR,113;0;7;FISHING,13;0;7;LANDING,0;1;6;INLAND,28;0;7;COASTAL,40;0;7;EROSION,50;0;8;SWIMMING,7;0;4;COVE,1;0;5;SHORE","gridSize":12,"difficulty":"easy","wordCount":12,"wordlist":["COVE","PIER","SHORE","INLAND","COASTAL","EROSION","FISHING","HARBOUR","LANDING","NEWPORT","TOURIST","SWIMMING"]}